nedry/__init__.py
nedry/__main__.py
nedry/command_processor.py
nedry/config.py
nedry/discord_bot.py
nedry/event_types.py
nedry/events.py
nedry/plugin.py
nedry/quotedb.json
nedry/quotes.py
nedry/twitch_monitor.py
nedry/utils.py
nedry/builtin_plugins/__init__.py
nedry/builtin_plugins/knock_knock_jokes.py
nedry/builtin_plugins/mock.py
nedry/builtin_plugins/schedule.py
nedry/builtin_plugins/social_credit.py
nedry/builtin_plugins/stories.py
nedry/builtin_plugins/trivia.py
nedry/builtin_plugins/wiki.py
nedry/builtin_plugins/writing_prompts.txt
nedry-2.4.3.dist-info/LICENSE
nedry-2.4.3.dist-info/METADATA
nedry-2.4.3.dist-info/WHEEL
nedry-2.4.3.dist-info/top_level.txt
nedry-2.4.3.dist-info/RECORD
