Metadata-Version: 2.1
Name: nedry
Version: 2.4.3
Summary: A fun & useful discord bot with a modular plugin system
Home-page: http://github.com/eriknyquist/nedry
Author: Erik Nyquist
Author-email: eknyquist@gmail.com
License: Apache 2.0
Platform: UNKNOWN
Requires-Python: >=3.9
Requires-Dist: requests
Requires-Dist: pytimeparse
Requires-Dist: twitch-python
Requires-Dist: versionedobj (>=2.0.3)
Requires-Dist: discord.py (==1.7.3)
Requires-Dist: discord (==1.7.3)
Requires-Dist: nltk
